poppy/__init__.py
poppy/accel_math.py
poppy/active_optics.py
poppy/dms.py
poppy/fresnel.py
poppy/fwcentroid.py
poppy/geometry.py
poppy/instrument.py
poppy/matrixDFT.py
poppy/misc.py
poppy/optics.py
poppy/physical_wavefront.py
poppy/poppy_core.py
poppy/special_prop.py
poppy/sub_sampled_optics.py
poppy/utils.py
poppy/version.py
poppy/wfe.py
poppy/zernike.py
poppy/tests/FITSFPMElement_test_result.fits
poppy/tests/__init__.py
poppy/tests/bowtie_fpm_0.05lamD.fits
poppy/tests/psd_wfe_ref_oap.fits
poppy/tests/test_accel_math.py
poppy/tests/test_active_optics.py
poppy/tests/test_core.py
poppy/tests/test_dms.py
poppy/tests/test_errorhandling.py
poppy/tests/test_fft.py
poppy/tests/test_fresnel.py
poppy/tests/test_fwcentroid.py
poppy/tests/test_geometry.py
poppy/tests/test_instrument.py
poppy/tests/test_matrixDFT.py
poppy/tests/test_matrixFTcoronagraph.py
poppy/tests/test_misc.py
poppy/tests/test_multiprocessing.py
poppy/tests/test_nonsquare.py
poppy/tests/test_optics.py
poppy/tests/test_physical_wavefront.py
poppy/tests/test_plotting.py
poppy/tests/test_sign_conventions.py
poppy/tests/test_special_prop.py
poppy/tests/test_sub_sampled_optics.py
poppy/tests/test_utils.py
poppy/tests/test_wavefront.py
poppy/tests/test_wfe.py
poppy/tests/test_zernike.py
poppy-1.1.1.dist-info/LICENSE.md
poppy-1.1.1.dist-info/METADATA
poppy-1.1.1.dist-info/WHEEL
poppy-1.1.1.dist-info/top_level.txt
poppy-1.1.1.dist-info/RECORD
