Metadata-Version: 2.1
Name: poppy
Version: 1.1.1
Summary: Physical optics propagation (wavefront diffraction) for optical simulations, particularly of telescopes.
Author-email: Marshall Perrin <mperrin@stsci.edu>
License: BSD-3-Clause
Project-URL: Homepage, https://github.com/spacetelescope/poppy
Project-URL: Documentation, https://poppy-optics.readthedocs.io/
Project-URL: Bug Tracker, https://github.com/spacetelescope/poppy/issues
Requires-Python: >=3.9
License-File: LICENSE.md
Requires-Dist: numpy (>=1.20.0)
Requires-Dist: scipy (>=1.5.0)
Requires-Dist: matplotlib (>=3.2.0)
Requires-Dist: astropy (>=4.3.0)
Provides-Extra: all
Requires-Dist: synphot ; extra == 'all'
Provides-Extra: docs
Requires-Dist: nbsphinx ; extra == 'docs'
Requires-Dist: stsci-rtd-theme ; extra == 'docs'
Requires-Dist: sphinx-astropy ; extra == 'docs'
Requires-Dist: sphinx-rtd-theme ; extra == 'docs'
Requires-Dist: sphinx-automodapi ; extra == 'docs'
Requires-Dist: sphinx-issues ; extra == 'docs'
Requires-Dist: tomli ; (python_version < "3.11") and extra == 'docs'
Provides-Extra: test
Requires-Dist: pytest ; extra == 'test'
Requires-Dist: pytest-astropy ; extra == 'test'
